simsoptpp.cpython-310-aarch64-linux-gnu.so
simsopt/__init__.py
simsopt/_version.py
simsopt/util/__init__.py
simsopt/util/mpi_logger.py
simsopt/util/fourier_interpolation.py
simsopt/util/famus_helpers.py
simsopt/util/mpi.py
simsopt/util/polarization_project.py
simsopt/util/constants.py
simsopt/util/log_config.yaml
simsopt/util/permanent_magnet_helper_functions.py
simsopt/util/logger.py
simsopt/_core/__init__.py
simsopt/_core/descriptor.py
simsopt/_core/finite_difference.py
simsopt/_core/util.py
simsopt/_core/json.py
simsopt/_core/derivative.py
simsopt/_core/dev.py
simsopt/_core/optimizable.py
simsopt/_core/types.py
simsopt/solve/__init__.py
simsopt/solve/permanent_magnet_optimization.py
simsopt/solve/mpi.py
simsopt/solve/serial.py
simsopt/solve/wireframe_optimization.py
simsopt/geo/finitebuild.py
simsopt/geo/curvexyzfouriersymmetries.py
simsopt/geo/surface.py
simsopt/geo/__init__.py
simsopt/geo/ports.py
simsopt/geo/curve.py
simsopt/geo/surfaceobjectives.py
simsopt/geo/boozersurface.py
simsopt/geo/wireframe_toroidal.py
simsopt/geo/surfacexyzfourier.py
simsopt/geo/jit.py
simsopt/geo/surfacehenneberg.py
simsopt/geo/curveplanarfourier.py
simsopt/geo/permanent_magnet_grid.py
simsopt/geo/curveobjectives.py
simsopt/geo/surfacexyztensorfourier.py
simsopt/geo/surfacerzfourier.py
simsopt/geo/plotting.py
simsopt/geo/framedcurve.py
simsopt/geo/qfmsurface.py
simsopt/geo/curvexyzfourier.py
simsopt/geo/curverzfourier.py
simsopt/geo/config.py
simsopt/geo/surfacegarabedian.py
simsopt/geo/strain_optimization.py
simsopt/geo/curveperturbed.py
simsopt/geo/curvehelical.py
simsopt/objectives/__init__.py
simsopt/objectives/utilities.py
simsopt/objectives/least_squares.py
simsopt/objectives/functions.py
simsopt/objectives/constrained.py
simsopt/objectives/fluxobjective.py
simsopt/configs/GIULIANI_length22_nsurfaces9.ma
simsopt/configs/__init__.py
simsopt/configs/NCSX.dat
simsopt/configs/GIULIANI_length22_nsurfaces9.currents
simsopt-1.10.2.dist-info/METADATA
simsopt-1.10.2.dist-info/RECORD
simsopt-1.10.2.dist-info/WHEEL
simsopt-1.10.2.dist-info/licenses/LICENSE
