Metadata-Version: 2.2
Name: simsopt
Version: 1.10.2
Summary: Framework for optimizing stellarators
Keywords: plasma physics,plasma,magnetohydrodynamics,mhd,nuclear fusion reactor,fusion,stellarator,vmec,spec,optimization,Biot-Savart,magnetostatics
Author-Email: Matt Landreman <mattland@umd.edu>, Bharat Medasani <mbkumar@gmail.com>, Florian Wechsung <wechsung@nyu.edu>
Maintainer-Email: Bharat Medasani <mbkumar@gmail.com>, Matt Landreman <mattland@umd.edu>
License: MIT License
Classifier: Development Status :: 5 - Production/Stable
Classifier: Intended Audience :: Science/Research
Classifier: Topic :: Scientific/Engineering :: Physics
Classifier: License :: OSI Approved :: MIT License
Classifier: Operating System :: MacOS :: MacOS X
Classifier: Operating System :: POSIX :: Linux
Classifier: Environment :: Console
Classifier: Programming Language :: Python :: 3 :: Only
Classifier: Programming Language :: Python :: 3.8
Classifier: Programming Language :: Python :: 3.9
Classifier: Programming Language :: Python :: 3.10
Project-URL: Homepage, https://github.com/hiddenSymmetries/simsopt
Project-URL: Download, https://pypi.org/project/simsopt
Project-URL: Issues, https://github.com/hiddenSymmetries/simsopt/issues
Project-URL: Documentation, https://simsopt.readthedocs.io
Project-URL: Repository, https://github.com/hiddenSymmetries/simsopt
Requires-Python: >=3.8
Requires-Dist: numpy>=1.21
Requires-Dist: jax>=0.2.5
Requires-Dist: jaxlib>=0.1.56
Requires-Dist: scipy>=1.5.4
Requires-Dist: Deprecated>=1.2.10
Requires-Dist: monty>=2021.6.10
Requires-Dist: ruamel.yaml
Requires-Dist: sympy
Requires-Dist: f90nml
Requires-Dist: pyevtk
Requires-Dist: matplotlib
Provides-Extra: spec
Requires-Dist: py_spec>=3.0.1; extra == "spec"
Requires-Dist: pyoculus>=0.1.1; extra == "spec"
Requires-Dist: h5py>=3.1.0; extra == "spec"
Provides-Extra: mpi
Requires-Dist: mpi4py>=3.0.3; extra == "mpi"
Provides-Extra: vis
Requires-Dist: vtk>=8.1.2; extra == "vis"
Requires-Dist: PyQt5; extra == "vis"
Requires-Dist: plotly; extra == "vis"
Requires-Dist: networkx; extra == "vis"
Provides-Extra: docs
Requires-Dist: sphinx; extra == "docs"
Requires-Dist: sphinx-rtd-theme; extra == "docs"
Requires-Dist: sphinxcontrib-napoleon; extra == "docs"
Requires-Dist: sphinx-autodoc-napoleon-typehints; extra == "docs"
Requires-Dist: breathe; extra == "docs"
Provides-Extra: algs
Requires-Dist: ground; extra == "algs"
Requires-Dist: bentley_ottmann; extra == "algs"
Requires-Dist: qsc; extra == "algs"
